PyTorch2Sklearn/CNN.py
PyTorch2Sklearn/MLP.py
PyTorch2Sklearn/MLP_AGNN.py
PyTorch2Sklearn/MLP_CNN.py
PyTorch2Sklearn/MLP_CNN_AGNN.py
PyTorch2Sklearn/Modules.py
PyTorch2Sklearn/Transformer.py
PyTorch2Sklearn/Transformer_AGNN.py
PyTorch2Sklearn/Transformer_CNN.py
PyTorch2Sklearn/Transformer_CNN_AGNN.py
PyTorch2Sklearn/__init__.py
PyTorch2Sklearn/__template__.py
PyTorch2Sklearn/environment.py
PyTorch2Sklearn/utils/__init__.py
PyTorch2Sklearn/utils/data.py
PyTorch2Sklearn-0.3.16.dist-info/LICENSE
PyTorch2Sklearn-0.3.16.dist-info/METADATA
PyTorch2Sklearn-0.3.16.dist-info/WHEEL
PyTorch2Sklearn-0.3.16.dist-info/top_level.txt
PyTorch2Sklearn-0.3.16.dist-info/RECORD
