Metadata-Version: 2.1
Name: PyTorch2Sklearn
Version: 0.3.16
Summary: Refactoring PyTorch models into sklearn-like API
Home-page: https://github.com/TGChenZP/PyTorch2Sklearn
Author: Lang Chen
Author-email: ronchen6666@gmail.com
License: UNKNOWN
Platform: UNKNOWN
Classifier: Programming Language :: Python :: 3
Classifier: License :: OSI Approved :: MIT License
Classifier: Operating System :: OS Independent
Requires-Python: >=3.6
License-File: LICENSE
